pypsi/__init__.py
pypsi/ansi.py
pypsi/cmdline.py
pypsi/completers.py
pypsi/core.py
pypsi/features.py
pypsi/format.py
pypsi/isolate.py
pypsi/namespace.py
pypsi/pipes.py
pypsi/progress.py
pypsi/release.py
pypsi/shell.py
pypsi/topics.py
pypsi/utils.py
pypsi/wizard.py
pypsi/commands/__init__.py
pypsi/commands/chdir.py
pypsi/commands/echo.py
pypsi/commands/exit.py
pypsi/commands/help.py
pypsi/commands/include.py
pypsi/commands/macro.py
pypsi/commands/pwd.py
pypsi/commands/system.py
pypsi/commands/tail.py
pypsi/commands/tip.py
pypsi/commands/xargs.py
pypsi/os/__init__.py
pypsi/os/unix.py
pypsi/os/win32.py
pypsi/plugins/__init__.py
pypsi/plugins/alias.py
pypsi/plugins/block.py
pypsi/plugins/cmd.py
pypsi/plugins/comment.py
pypsi/plugins/hexcode.py
pypsi/plugins/history.py
pypsi/plugins/multiline.py
pypsi/plugins/variable.py
pypsi-1.4.7.dist-info/LICENSE
pypsi-1.4.7.dist-info/METADATA
pypsi-1.4.7.dist-info/WHEEL
pypsi-1.4.7.dist-info/top_level.txt
pypsi-1.4.7.dist-info/RECORD
