Metadata-Version: 2.2
Name: pypsi
Version: 1.4.7
Summary: Python Pluggable Shell Interface
Home-page: https://github.com/ameily/pypsi
Download-URL: https://pypi.python.org/pypi/pypsi
Author: Adam Meily
Author-email: meily.adam@gmail.com
License: ISC
Keywords: cli,command line,command line interface,shell,terminal,console,term,command prompt
Classifier: Development Status :: 5 - Production/Stable
Classifier: Environment :: Console
Classifier: Intended Audience :: Developers
Classifier: License :: OSI Approved :: ISC License (ISCL)
Classifier: Natural Language :: English
Classifier: Operating System :: OS Independent
Classifier: Programming Language :: Python
Classifier: Programming Language :: Python :: 3
Classifier: Topic :: Software Development :: User Interfaces
Classifier: Topic :: Software Development :: Libraries :: Application Frameworks
Classifier: Topic :: Terminals
License-File: LICENSE
Requires-Dist: chardet>=2.0.1
Requires-Dist: pyreadline>=2.1; platform_system == "Windows"
Provides-Extra: dev
Requires-Dist: pytest>=3.6.2; extra == "dev"
Requires-Dist: pytest-cov>=2.5.1; extra == "dev"
Requires-Dist: pylint<=2.11.1; extra == "dev"
Requires-Dist: pycodestyle>=2.4.0; extra == "dev"
Requires-Dist: coverage; extra == "dev"
Dynamic: author
Dynamic: author-email
Dynamic: classifier
Dynamic: description
Dynamic: download-url
Dynamic: home-page
Dynamic: keywords
Dynamic: license
Dynamic: provides-extra
Dynamic: requires-dist
Dynamic: summary
